pyvmt/__init__.py
pyvmt/__main__.py
pyvmt/composer.py
pyvmt/environment.py
pyvmt/exceptions.py
pyvmt/model.py
pyvmt/operators.py
pyvmt/properties.py
pyvmt/renamer.py
pyvmt/shortcuts.py
pyvmt/substituters.py
pyvmt/solvers/__init__.py
pyvmt/solvers/euforia.py
pyvmt/solvers/ic3ia.py
pyvmt/solvers/nuxmv.py
pyvmt/solvers/solver.py
pyvmt/solvers/traces.py
pyvmt/vmtlib/__init__.py
pyvmt/vmtlib/annotations.py
pyvmt/vmtlib/commands.py
pyvmt/vmtlib/parser.py
pyvmt/vmtlib/printers.py
pyvmt/vmtlib/reader.py
pyvmt-0.0.4.dist-info/LICENSE
pyvmt-0.0.4.dist-info/METADATA
pyvmt-0.0.4.dist-info/WHEEL
pyvmt-0.0.4.dist-info/top_level.txt
pyvmt-0.0.4.dist-info/RECORD
