Metadata-Version: 2.1
Name: pyvmt
Version: 0.0.4
Summary: Library to create and check finite and infinite state transition systems
Home-page: https://github.com/pyvmt/pyvmt
Author: PyVmt team
Author-email: agirardi@fbk.eu
License: APACHE
Platform: UNKNOWN
Classifier: Programming Language :: Python :: 3
Classifier: License :: OSI Approved :: Apache Software License
Requires-Python: >=3.7
License-File: LICENSE
Requires-Dist: pysmt
